{
  "breadcrumb": [
    "电费相关/",
    "电费相关",
    "异常每日盘点/",
    "异常每日盘点"
  ],
  "tabs": [],
  "labels": [
    "当前查看项目为：",
    "不计费",
    "后付费",
    "预付费",
    "仅抄表",
    "机房群控",
    "按天",
    "按小时",
    "氟机",
    "直膨机",
    "温控器",
    "水机",
    "盘点日期范围:",
    "仅看此时间段新异常",
    "主机异常（0个）",
    "主机离线（0个）",
    "存储空间不够（0个）",
    "抄电表异常（0个）",
    "由主机离线造成（0个）",
    "由抄表失败造成（0个）",
    "由电表离线造成（0个）",
    "电表未绑外机（0个）",
    "能抄到表（0个）",
    "没抄到表（0个）",
    "电表外机可能绑错（0个）",
    "有电量没当量（0个）",
    "有当量没电量（0个）",
    "外机未绑电表（0个）",
    "有用量（0个）",
    "无用量（0个）",
    "内机未绑定建筑物（0个）"
  ],
  "inputs": [
    {
      "ph": "请选择",
      "val": "1861蔚蓝公寓B2"
    },
    {
      "ph": "",
      "val": ""
    },
    {
      "ph": "请选择",
      "val": "20条/页"
    },
    {
      "ph": "",
      "val": "1"
    }
  ],
  "buttons": [
    {
      "text": "重置筛选",
      "cls": "el-button--primary"
    },
    {
      "text": "关闭",
      "cls": "el-button--default"
    },
    {
      "text": "绑定",
      "cls": "el-button--primary"
    },
    {
      "text": "已知晓",
      "cls": "el-button--default"
    }
  ],
  "tables": [
    {
      "headers": [
        "项目",
        "盘点日期",
        "异常类型",
        "异常对象",
        "关键信息"
      ],
      "rows": []
    }
  ],
  "pagination": [
    "共 0 条10条/页20条/页30条/页50条/页1前往页"
  ],
  "cardTitles": [],
  "_route": "/abnormalInventory/index",
  "_label": "异常每日盘点",
  "_finalUrl": "https://m.achelp.cn/abnormalInventory/index"
}